datastand/__init__.py
datastand/datastand.py
datastand-2.5.0.dist-info/LICENSE
datastand-2.5.0.dist-info/METADATA
datastand-2.5.0.dist-info/WHEEL
datastand-2.5.0.dist-info/RECORD
