Metadata-Version: 2.1
Name: datastand
Version: 2.5.0
Summary: A python package to help Data Scientists, Machine Learning Engineers and Analysts better understand data. Gives quick insights about given data; general dataset statistics, shape of dataset, number of unique data types, number of numerical and non-numerical columns, missing data statistics, missing data heatmap and provides methodology to impute missing data.
Author: lyraxvincent
Author-email: njongevincent@gmail.com
Requires-Python: >=3.9,<3.13
Classifier: Programming Language :: Python :: 3
Classifier: Programming Language :: Python :: 3.9
Classifier: Programming Language :: Python :: 3.10
Classifier: Programming Language :: Python :: 3.11
Requires-Dist: matplotlib (>=3.8.0,<4.0.0)
Requires-Dist: numpy (>=1.26.0,<2.0.0)
Requires-Dist: pandas (>=2.1.1,<3.0.0)
Requires-Dist: seaborn (>=0.12.2,<0.13.0)
